Trees/BST.py
Trees/BinaryTree.py
mr123-1.0.0.dist-info/LICENSE
mr123-1.0.0.dist-info/METADATA
mr123-1.0.0.dist-info/WHEEL
mr123-1.0.0.dist-info/entry_points.txt
mr123-1.0.0.dist-info/top_level.txt
mr123-1.0.0.dist-info/RECORD
