Metadata-Version: 2.1
Name: mr123
Version: 1.0.0
Summary: Read the latest Real Python tutorials
Home-page: UNKNOWN
Author: mr
License: MIT
Platform: UNKNOWN
Classifier: License :: OSI Approved :: MIT License
Classifier: Programming Language :: Python :: 3
Classifier: Programming Language :: Python :: 3.7
